README.md
setup.cfg
setup.py
circle_evolution/__init__.py
circle_evolution/__main__.py
circle_evolution/evolution.py
circle_evolution/fitness.py
circle_evolution/helpers.py
circle_evolution/main.py
circle_evolution/species.py
circle_evolution.egg-info/PKG-INFO
circle_evolution.egg-info/SOURCES.txt
circle_evolution.egg-info/dependency_links.txt
circle_evolution.egg-info/entry_points.txt
circle_evolution.egg-info/requires.txt
circle_evolution.egg-info/top_level.txt