Metadata-Version: 2.1
Name: circle-evolution
Version: 0.1
Summary: Evolutionary Art Using Circles
Home-page: https://github.com/ahmedkhalf/Circle-Evolution/
Author: Ahmed Khalf, Guilherme de Amorim
Author-email: ahmedkhalf567@gmail.com, ggimenezjr@gmail.com
License: UNKNOWN
Download-URL: https://github.com/ahmedkhalf/Circle-Evolution/archive/v0.1.tar.gz
Platform: UNKNOWN
Classifier: Intended Audience :: Developers
Classifier: Intended Audience :: Science/Research
Classifier: Programming Language :: Python
Classifier: Programming Language :: Python :: 3
Classifier: Programming Language :: Python :: 3.6
Classifier: Programming Language :: Python :: 3.7
Classifier: Topic :: Software Development
Requires-Python: >=3.6
Provides-Extra: test
